{
    "word_count": 2932,
    "unique_word_count": 947,
    "word_frequency": {
        "dan": 49,
        "grad": 40,
        "oko": 37,
        "ruka": 36,
        "hodati": 34,
        "misliti": 33,
        "voleti": 31,
        "znam": 27,
        "tamo": 26,
        "redak": 26,
        "videti": 23,
        "ljubav": 23,
        "kraj": 22,
        "voditi": 22,
        "vreme": 21,
        "ljudi": 19,
        "put": 19,
        "dobro": 19,
        "kazati": 19,
        "imati": 19,
        "hladan": 17,
        "svet": 17,
        "zaborav": 17,
        "znak": 16,
        "mrak": 14,
        "trebati": 14,
        "spavati": 14,
        "noc": 14,
        "prvi": 14,
        "stvarati": 14,
        "ovde": 13,
        "trag": 13,
        "opet": 13,
        "jedan": 13,
        "gledati": 13,
        "glas": 12,
        "lice": 12,
        "zid": 12,
        "iznad": 12,
        "glad": 12,
        "svako": 12,
        "boliti": 12,
        "svaki": 11,
        "strah": 11,
        "biti": 11,
        "nositi": 11,
        "ispod": 11,
        "usnuti": 10,
        "vetar": 10,
        "ostati": 10,
        "svetlo": 10,
        "godina": 10,
        "roditi": 10,
        "uvek": 10,
        "nemati": 10,
        "zvoniti": 10,
        "odlaziti": 9,
        "moj": 9,
        "iza": 9,
        "dete": 9,
        "dno": 9,
        "glava": 9,
        "krenuti": 9,
        "mnogo": 9,
        "dolaziti": 9,
        "reklama": 9,
        "pogledati": 9,
        "mozes": 9,
        "koliko": 9,
        "daleko": 8,
        "aut": 8,
        "tonuti": 8,
        "zemlja": 8,
        "hladno": 8,
        "stvar": 8,
        "miris": 8,
        "dugo": 8,
        "tvoj": 8,
        "promeniti": 8,
        "unatrag": 8,
        "novac": 8,
        "zima": 7,
        "ostaviti": 7,
        "osecam": 7,
        "dah": 7,
        "plav": 7,
        "koza": 7,
        "dodir": 7,
        "korak": 7,
        "praviti": 7,
        "bez": 7,
        "drugi": 7,
        "topao": 7,
        "vratiti": 7,
        "bojati": 7,
        "negde": 6,
        "zlo": 6,
        "zasto": 6,
        "zvati": 6,
        "ostajati": 6,
        "suma": 6,
        "sasvim": 6,
        "dobar": 6,
        "prazan": 6,
        "pogled": 6,
        "noga": 6,
        "ulica": 6,
        "san": 6,
        "kamen": 6,
        "malo": 6,
        "vrat": 6,
        "kakav": 6,
        "crn": 6,
        "krug": 6,
        "snaga": 6,
        "dosta": 6,
        "dlan": 6,
        "nikad": 6,
        "prst": 6,
        "soba": 6,
        "kap": 6,
        "gubiti": 6,
        "jesen": 6,
        "prolaziti": 6,
        "dosada": 6,
        "govoriti": 6,
        "oni": 6,
        "zelen": 6,
        "poslednji": 6,
        "slomiti": 6,
        "verovati": 6,
        "teg": 6,
        "slobodan": 6,
        "ovaj": 5,
        "krv": 5,
        "srce": 5,
        "sretati": 5,
        "pravo": 5,
        "pred": 5,
        "postojati": 5,
        "prodati": 5,
        "granica": 5,
        "par": 5,
        "svoj": 5,
        "telo": 5,
        "suv": 5,
        "sunce": 5,
        "zub": 5,
        "bol": 5,
        "nemoj": 5,
        "osloniti": 5,
        "menjati": 5,
        "kucati": 5,
        "modar": 5,
        "uliti": 5,
        "pustiti": 5,
        "senka": 5,
        "siguran": 5,
        "odmor": 5,
        "receiver": 5,
        "sarajevski": 5,
        "nikako": 4,
        "umoran": 4,
        "mesec": 4,
        "vatra": 4,
        "plakati": 4,
        "mirno": 4,
        "pramen": 4,
        "niko": 4,
        "tajna": 4,
        "otvoriti": 4,
        "staklo": 4,
        "kriti": 4,
        "hteti": 4,
        "tko": 4,
        "hej": 4,
        "mam": 4,
        "radi": 4,
        "zena": 4,
        "oblak": 4,
        "sanjati": 4,
        "vod": 4,
        "vezati": 4,
        "more": 4,
        "sav": 4,
        "saznati": 4,
        "meso": 4,
        "duh": 4,
        "hrana": 4,
        "isti": 4,
        "sklopiti": 4,
        "ime": 4,
        "usna": 4,
        "morati": 4,
        "izgubiti": 4,
        "posmatrati": 4,
        "lak": 4,
        "nokat": 4,
        "kupa": 4,
        "odgovor": 4,
        "grudi": 4,
        "kutak": 4,
        "zelje": 4,
        "danas": 4,
        "prevara": 4,
        "radostan": 4,
        "postajati": 4,
        "vrt": 4,
        "stablo": 4,
        "umirati": 4,
        "spoljni": 4,
        "dolazak": 4,
        "cisterna": 4,
        "mogul": 4,
        "znalac": 4,
        "jedrenje": 4,
        "proslediti": 4,
        "dosadno": 3,
        "mesto": 3,
        "iznutra": 3,
        "sam": 3,
        "sakriti": 3,
        "kost": 3,
        "beskrajno": 3,
        "primiti": 3,
        "skloniti": 3,
        "nista": 3,
        "stati": 3,
        "potpuno": 3,
        "mrtav": 3,
        "tren": 3,
        "vladati": 3,
        "zaboraviti": 3,
        "birati": 3,
        "sedam": 3,
        "hvatati": 3,
        "igrati": 3,
        "uzimati": 3,
        "ipak": 3,
        "reka": 3,
        "kuda": 3,
        "posao": 3,
        "zivot": 3,
        "sada": 3,
        "jak": 3,
        "glup": 3,
        "uho": 3,
        "zvuk": 3,
        "sad": 3,
        "kosa": 3,
        "voda": 3,
        "popiti": 3,
        "isto": 3,
        "prepoznati": 3,
        "nekad": 3,
        "velik": 3,
        "svetao": 3,
        "moliti": 3,
        "crven": 3,
        "razlog": 3,
        "buditi": 3,
        "smisliti": 3,
        "pokazati": 3,
        "navika": 3,
        "govor": 3,
        "nova": 3,
        "obala": 3,
        "znoj": 3,
        "oblik": 3,
        "shvatiti": 3,
        "smeti": 3,
        "njen": 3,
        "ponos": 3,
        "brdo": 3,
        "dosaditi": 3,
        "probuditi": 3,
        "bezimen": 3,
        "theta": 3,
        "ideja": 3,
        "set": 3,
        "prosuti": 3,
        "zabavno": 2,
        "levo": 2,
        "desno": 2,
        "cilj": 2,
        "lako": 2,
        "brzo": 2,
        "rasti": 2,
        "paziti": 2,
        "blago": 2,
        "anestezija": 2,
        "srebrn": 2,
        "zamisliti": 2,
        "zvezda": 2,
        "zavijati": 2,
        "zaplesti": 2,
        "prestati": 2,
        "ptica": 2,
        "dalek": 2,
        "niz": 2,
        "prozor": 2,
        "ostavljati": 2,
        "sob": 2,
        "hiljada": 2,
        "dignuti": 2,
        "staklen": 2,
        "poraz": 2,
        "odakle": 2,
        "krov": 2,
        "pitati": 2,
        "stradati": 2,
        "zaprljati": 2,
        "nebo": 2,
        "pucati": 2,
        "zgrada": 2,
        "magla": 2,
        "zapad": 2,
        "svuda": 2,
        "bluz": 2,
        "nervozan": 2,
        "gvozden": 2,
        "stiskati": 2,
        "svega": 2,
        "budan": 2,
        "rastanak": 2,
        "disati": 2,
        "javljati": 2,
        "pitanje": 2,
        "surov": 2,
        "pisati": 2,
        "milost": 2,
        "kriv": 2,
        "zakon": 2,
        "skrivati": 2,
        "glasati": 2,
        "gladan": 2,
        "sat": 2,
        "peta": 2,
        "tek": 2,
        "ritam": 2,
        "uzdah": 2,
        "jezik": 2,
        "jastuk": 2,
        "baciti": 2,
        "most": 2,
        "sve": 2,
        "sjati": 2,
        "strana": 2,
        "istina": 2,
        "grlo": 2,
        "sediti": 2,
        "pariti": 2,
        "pijan": 2,
        "stanje": 2,
        "zrno": 2,
        "strpati": 2,
        "duvati": 2,
        "putovati": 2,
        "mala": 2,
        "poznavati": 2,
        "javiti": 2,
        "jadranski": 2,
        "nemiran": 2,
        "raditi": 2,
        "star": 2,
        "ljubiti": 2,
        "usta": 2,
        "brod": 2,
        "stranica": 2,
        "ustajati": 2,
        "lanac": 2,
        "sakrivati": 2,
        "osloboditi": 2,
        "otvor": 2,
        "drug": 2,
        "polako": 2,
        "milja": 2,
        "krevet": 2,
        "stolica": 2,
        "preko": 2,
        "hodnik": 2,
        "trava": 2,
        "putem": 2,
        "dati": 2,
        "ograda": 2,
        "ribati": 2,
        "dobiti": 2,
        "stalno": 2,
        "taman": 2,
        "izlaz": 2,
        "dalj": 2,
        "osetiti": 2,
        "spustiti": 2,
        "iskrenost": 2,
        "potreban": 2,
        "covek": 2,
        "novina": 2,
        "pratiti": 2,
        "stalan": 2,
        "bacati": 2,
        "zora": 2,
        "povratak": 2,
        "igra": 2,
        "neki": 2,
        "dovoljan": 2,
        "rast": 2,
        "pokret": 2,
        "onako": 2,
        "skript": 2,
        "zatvoriti": 2,
        "porozan": 2,
        "posle": 2,
        "zaboravljati": 2,
        "polje": 2,
        "onaj": 2,
        "potruditi": 2,
        "pevati": 2,
        "kristalan": 2,
        "blato": 2,
        "inje": 2,
        "zrak": 2,
        "brat": 2,
        "maskirati": 2,
        "zavesa": 2,
        "pesma": 2,
        "poljubiti": 2,
        "njihov": 2,
        "tiho": 2,
        "taj": 2,
        "haljina": 2,
        "pokrenuti": 2,
        "rupa": 2,
        "mokar": 2,
        "opasati": 2,
        "nailaziti": 2,
        "pad": 2,
        "umor": 2,
        "prazniti": 2,
        "pustinja": 2,
        "puniti": 2,
        "autobus": 2,
        "telefon": 2,
        "nauk": 2,
        "urediti": 2,
        "sopstven": 2,
        "zabranjivati": 2,
        "osvojiti": 2,
        "zatrpati": 2,
        "nasilan": 2,
        "garda": 2,
        "otjecanje": 2,
        "mrsan": 2,
        "cuclati": 2,
        "celzij": 2,
        "belgijski": 2,
        "naspavati": 2,
        "saplesti": 2,
        "oticanje": 2,
        "bezveznjak": 2,
        "zategnutost": 2,
        "docent": 2,
        "satenski": 2,
        "slatko": 1,
        "gaziti": 1,
        "zrcalo": 1,
        "otvarati": 1,
        "odvesti": 1,
        "lagano": 1,
        "jug": 1,
        "osvrnuti": 1,
        "nizati": 1,
        "isprati": 1,
        "zavidan": 1,
        "ponovo": 1,
        "nezgodno": 1,
        "kliziti": 1,
        "gol": 1,
        "brojati": 1,
        "puta": 1,
        "tupiti": 1,
        "strastan": 1,
        "pet": 1,
        "lomiti": 1,
        "kristal": 1,
        "iskriti": 1,
        "potpun": 1,
        "stranac": 1,
        "napraviti": 1,
        "trzati": 1,
        "promicati": 1,
        "uzdisati": 1,
        "raspadati": 1,
        "vrediti": 1,
        "trud": 1,
        "sigurno": 1,
        "zato": 1,
        "odluka": 1,
        "kopati": 1,
        "debeo": 1,
        "potreba": 1,
        "tron": 1,
        "doticati": 1,
        "poznati": 1,
        "trenutak": 1,
        "pogodno": 1,
        "momenat": 1,
        "leden": 1,
        "kor": 1,
        "predivan": 1,
        "balkon": 1,
        "divlji": 1,
        "atlas": 1,
        "kugla": 1,
        "mit": 1,
        "legenda": 1,
        "vrebati": 1,
        "dvojiti": 1,
        "beskrajan": 1,
        "siv": 1,
        "metalan": 1,
        "tlo": 1,
        "vrh": 1,
        "dopirati": 1,
        "zastava": 1,
        "kihati": 1,
        "korito": 1,
        "otisak": 1,
        "rosa": 1,
        "prelazak": 1,
        "postavljati": 1,
        "sin": 1,
        "strepiti": 1,
        "radost": 1,
        "revolver": 1,
        "pazuh": 1,
        "pola": 1,
        "kratko": 1,
        "okvir": 1,
        "razgovor": 1,
        "problem": 1,
        "pretvoriti": 1,
        "zgaziti": 1,
        "taka": 1,
        "ukus": 1,
        "gladak": 1,
        "pojas": 1,
        "puls": 1,
        "prolaznik": 1,
        "grbav": 1,
        "krupan": 1,
        "zvonak": 1,
        "oprati": 1,
        "obrijati": 1,
        "toplo": 1,
        "kockati": 1,
        "krvav": 1,
        "selo": 1,
        "spaliti": 1,
        "greh": 1,
        "muzika": 1,
        "realan": 1,
        "ikona": 1,
        "nestajati": 1,
        "drag": 1,
        "strast": 1,
        "mora": 1,
        "visiti": 1,
        "rameni": 1,
        "kupatilo": 1,
        "otac": 1,
        "prati": 1,
        "ogroman": 1,
        "pljusak": 1,
        "ti": 1,
        "stenjati": 1,
        "ubod": 1,
        "stotina": 1,
        "mali": 1,
        "igla": 1,
        "teret": 1,
        "kafa": 1,
        "solo": 1,
        "smrt": 1,
        "iva": 1,
        "pojesti": 1,
        "novo": 1,
        "jutro": 1,
        "spojiti": 1,
        "zameniti": 1,
        "usloviti": 1,
        "pogodnost": 1,
        "procvat": 1,
        "prevelik": 1,
        "sredstvo": 1,
        "zdrav": 1,
        "prednje": 1,
        "poslati": 1,
        "snimati": 1,
        "poneki": 1,
        "razumeti": 1,
        "trepet": 1,
        "napatiti": 1,
        "vucarati": 1,
        "talas": 1,
        "truo": 1,
        "hrast": 1,
        "bujica": 1,
        "jesenji": 1,
        "donji": 1,
        "slava": 1,
        "jesti": 1,
        "progutati": 1,
        "prokleto": 1,
        "let": 1,
        "som": 1,
        "lopov": 1,
        "pila": 1,
        "groznica": 1,
        "ugao": 1,
        "pust": 1,
        "truba": 1,
        "uzbuna": 1,
        "bor": 1,
        "listati": 1,
        "knjiga": 1,
        "nakovanj": 1,
        "pun": 1,
        "brigati": 1,
        "nocas": 1,
        "mlad": 1,
        "ljut": 1,
        "tama": 1,
        "sara": 1,
        "prekidati": 1,
        "stvoriti": 1,
        "razbiti": 1,
        "rasuti": 1,
        "razbijati": 1,
        "skupiti": 1,
        "aha": 1,
        "zabrana": 1,
        "dozvola": 1,
        "zabava": 1,
        "hajde": 1,
        "izgled": 1,
        "zamrsiti": 1,
        "linija": 1,
        "kud": 1,
        "god": 1,
        "odavno": 1,
        "starati": 1,
        "slon": 1,
        "indijski": 1,
        "boriti": 1,
        "blizu": 1,
        "stan": 1,
        "kutija": 1,
        "plesti": 1,
        "morski": 1,
        "primati": 1,
        "promena": 1,
        "lane": 1,
        "voden": 1,
        "zalazak": 1,
        "kidati": 1,
        "platno": 1,
        "seno": 1,
        "duo": 1,
        "ugasiti": 1,
        "jezero": 1,
        "mirisan": 1,
        "napadati": 1,
        "dom": 1,
        "plamen": 1,
        "oduzeti": 1,
        "ja": 1,
        "neon": 1,
        "slika": 1,
        "masan": 1,
        "poslovan": 1,
        "prljavo": 1,
        "ulaz": 1,
        "padati": 1,
        "med": 1,
        "levi": 1,
        "gurati": 1,
        "vidra": 1,
        "bedro": 1,
        "skupljati": 1,
        "nevolja": 1,
        "izgovor": 1,
        "zakasniti": 1,
        "nasloviti": 1,
        "rubrika": 1,
        "grebati": 1,
        "naslon": 1,
        "grom": 1,
        "hrom": 1,
        "micati": 1,
        "tom": 1,
        "tragati": 1,
        "prijatelj": 1,
        "klupa": 1,
        "vest": 1,
        "upravo": 1,
        "braniti": 1,
        "slaviti": 1,
        "nadati": 1,
        "gristi": 1,
        "devet": 1,
        "kod": 1,
        "racija": 1,
        "tuda": 1,
        "poverljiv": 1,
        "predati": 1,
        "asfalt": 1,
        "glavni": 1,
        "policija": 1,
        "predavati": 1,
        "film": 1,
        "ujutro": 1,
        "utorak": 1,
        "betonski": 1,
        "pastir": 1,
        "visok": 1,
        "platforma": 1,
        "stran": 1,
        "obzir": 1,
        "tup": 1,
        "brinuti": 1,
        "ludost": 1,
        "glupost": 1,
        "plaziti": 1,
        "dubok": 1,
        "nestvaran": 1,
        "prav": 1,
        "jedini": 1,
        "istinski": 1,
        "nalik": 1,
        "praznik": 1,
        "crveno": 1,
        "crnac": 1,
        "struk": 1,
        "bura": 1,
        "ponaosob": 1,
        "opipati": 1,
        "svilen": 1,
        "suknja": 1,
        "ispit": 1,
        "napis": 1,
        "crtati": 1,
        "zmaj": 1,
        "izbrisati": 1,
        "potraga": 1,
        "staviti": 1,
        "zakloniti": 1,
        "pokloniti": 1,
        "uzeti": 1,
        "grliti": 1,
        "hod": 1,
        "boja": 1,
        "sastaviti": 1,
        "poruka": 1,
        "oprezan": 1,
        "ples": 1,
        "topiti": 1,
        "odustati": 1,
        "parola": 1,
        "mleko": 1,
        "kolac": 1,
        "prljav": 1,
        "mrlja": 1,
        "popodne": 1,
        "led": 1,
        "opadati": 1,
        "lisac": 1,
        "veza": 1,
        "koji": 1,
        "bistar": 1,
        "planinski": 1,
        "dodirivati": 1,
        "poseban": 1,
        "obred": 1,
        "svestan": 1,
        "padanje": 1,
        "zatvarati": 1,
        "unutra": 1,
        "sumnja": 1,
        "gurnuti": 1,
        "podsticati": 1,
        "popeti": 1,
        "obraz": 1,
        "sjuriti": 1,
        "metak": 1,
        "ishod": 1,
        "postati": 1,
        "poroditi": 1,
        "kasnije": 1,
        "generacija": 1,
        "igranje": 1,
        "lopta": 1,
        "bas": 1,
        "tim": 1,
        "delo": 1,
        "cesta": 1,
        "podne": 1,
        "lipa": 1,
        "roditelj": 1,
        "uspomena": 1,
        "pretvarati": 1,
        "podsticaj": 1,
        "jako": 1,
        "paliti": 1,
        "tinjati": 1,
        "viriti": 1,
        "rukav": 1,
        "otrov": 1,
        "ispitivati": 1,
        "obarati": 1,
        "alibi": 1,
        "uloga": 1,
        "veliko": 1,
        "prolaz": 1,
        "dotaknuti": 1,
        "iznova": 1,
        "gledanje": 1,
        "piti": 1,
        "sok": 1,
        "kajanje": 1,
        "fabrika": 1,
        "trka": 1,
        "park": 1,
        "duboko": 1,
        "podrum": 1,
        "rub": 1,
        "uputiti": 1,
        "netko": 1,
        "sklapati": 1,
        "zatvor": 1,
        "zamotati": 1,
        "umotati": 1,
        "poklopiti": 1,
        "udahnuti": 1,
        "opustiti": 1,
        "otpustiti": 1,
        "poneti": 1,
        "matica": 1,
        "ugriz": 1,
        "kupiti": 1,
        "kolati": 1,
        "list": 1,
        "lokva": 1,
        "skok": 1,
        "zadnji": 1,
        "prasak": 1,
        "jednom": 1,
        "leto": 1,
        "leteti": 1,
        "venuti": 1,
        "kupati": 1,
        "podloga": 1,
        "naivan": 1,
        "zamak": 1,
        "zavist": 1,
        "bolest": 1,
        "dubina": 1,
        "plac": 1,
        "ivan": 1,
        "zoran": 1,
        "dozvoleti": 1,
        "oda": 1,
        "borba": 1,
        "protiv": 1,
        "razum": 1,
        "valjda": 1,
        "zajedno": 1,
        "spas": 1,
        "prepoznavati": 1,
        "grana": 1,
        "pokrov": 1,
        "oprost": 1,
        "deo": 1,
        "sloboda": 1,
        "gotovo": 1,
        "tad": 1,
        "prvo": 1,
        "smiriti": 1,
        "lutka": 1,
        "lovac": 1,
        "luk": 1,
        "mrtvilo": 1,
        "pomiriti": 1,
        "pas": 1,
        "nahraniti": 1,
        "dodirnuti": 1,
        "nedodirljiv": 1,
        "spasiti": 1,
        "prema": 1,
        "bubuljica": 1,
        "izbeglica": 1,
        "proslov": 1,
        "citat": 1,
        "grcati": 1,
        "idol": 1,
        "sidro": 1,
        "lepinja": 1,
        "blistav": 1,
        "tamnica": 1,
        "napiti": 1,
        "borik": 1,
        "sistem": 1,
        "trganje": 1,
        "suputnik": 1,
        "biceps": 1,
        "nacrt": 1,
        "uslediti": 1,
        "playboy": 1,
        "moderno": 1,
        "jaslice": 1,
        "znamenit": 1,
        "suvisao": 1,
        "neznatan": 1,
        "slovenac": 1,
        "prljavac": 1,
        "nemac": 1,
        "unositi": 1,
        "tretirati": 1,
        "izlizanost": 1,
        "citirati": 1,
        "nepovratan": 1,
        "nadebljati": 1,
        "naboran": 1,
        "tucet": 1,
        "konac": 1,
        "stegnuti": 1,
        "sakupiti": 1,
        "tanker": 1,
        "zicer": 1,
        "podignuti": 1,
        "lampica": 1,
        "nasapunati": 1,
        "cik": 1,
        "bezalkoholan": 1,
        "loza": 1,
        "ruski": 1,
        "nenadan": 1,
        "zasluga": 1
    }
}